pyEX/zipline/__init__.py
pyEX/zipline/_version.py
pyEX/zipline/ingest.py
pyEX.zipline-0.0.7.dist-info/LICENSE
pyEX.zipline-0.0.7.dist-info/METADATA
pyEX.zipline-0.0.7.dist-info/WHEEL
pyEX.zipline-0.0.7.dist-info/top_level.txt
pyEX.zipline-0.0.7.dist-info/RECORD
